README.md
setup.cfg
setup.py
gildcivility_helpers/__init__.py
gildcivility_helpers/civility_db.py
gildcivility_helpers/reddit.py
gildcivility_helpers/sms.py
gildcivility_helpers/tools.py
gildcivility_helpers.egg-info/PKG-INFO
gildcivility_helpers.egg-info/SOURCES.txt
gildcivility_helpers.egg-info/dependency_links.txt
gildcivility_helpers.egg-info/requires.txt
gildcivility_helpers.egg-info/top_level.txt